[
    {
      "Brand": "ASUS",
      "BrandName": "ASUS",
      "Category": "Graphics Card",
      "ProductName": "TUF GeForce RTX 4090 OC",
      "RAM": "24 GB",
      "Description": "NVIDIA Ada Lovelace Streaming Multiprocessors: Up to 2x performance and power efficiency, 4th Generation Tensor Cores: Up to 2X AI performance, 3rd Generation RT Cores: Up to 2X ray tracing performance, Axial-tech fans scaled up for 23% more airflow, and Dual Ball Fan Bearings last up to twice as long as conventional designs.",
      "Price": 1655.95,
      "MSRP": 1709.99,
      "QtyOnHand": 17,
      "QtyOnBackOrder": 2,
      "GraphicName": "ASUS TUF GeForce RTX 4090 OC.png",
      "Memory": "NVIDIA Ada Lovelace Streaming Multiprocessors: Up to 2x performance and power efficiency",
      "Processor": "4th Generation Tensor Cores: Up to 2X AI performance",
      "Graphics": "3rd Generation RT Cores: Up to 2X ray tracing performance",
      "Storage": "Axial-tech fans scaled up for 23% more airflow"
    },
    {
      "Brand": "Acer",
      "BrandName": "Acer",
      "Category": "Laptop",
      "ProductName": "Acer Nitro 17 Gaming",
      "RAM": "16 GB",
      "Description": "Featuring the latest AMD Ryzen 7000 Series Processors and NVIDIAs DLSS 3 technology. The picture-perfect 17.3-inch QHD display with 165Hz refresh rates provides an immersive viewing experience while next-gen cooling, a 4-zone RGB keyboard and NitroSense software let you take command of the playing field. AMD Ryzen 7000 Series: Now featuring the AMD Ryzen 7 7735HS Octa-Core Processor delivering superior gaming performance where you need it most. With Precision Boost, get up to 4.75GHz for your high-demand games. They're powered by the ultra-efficient NVIDIA Ada Lovelace architecture which delivers a quantum leap in both performance and AI-powered graphics.",
      "Price": 1699.99,
      "MSRP": 1999.99,
      "QtyOnHand": 14,
      "QtyOnBackOrder": 3,
      "GraphicName": "Acer Nitro 17 Gaming Laptop.png",
      "Memory": "16GB DDR5 Memory, 512GB PCIe Gen 4 SSD (1 - PCIe M.2 Slot Available) & microSD Card Reader",
      "Processor": "AMD Ryzen 5 7535HS Hexa-Core Processor",
      "Graphics": "Overclockable NVIDIA GeForce RTX 4050 Laptop GPU with 6GB of dedicated GDDR6 VRAM",
      "Storage": "512 GB"
    },
    {
      "Brand": "ASUS",
      "BrandName": "ASUS",
      "Category": "Graphics Card",
      "ProductName": "TUF GeForce RTX® 4080 OC",
      "RAM": "16 GB",
      "Description": "NVIDIA Ada Lovelace Streaming Multiprocessors: Up to 2x performance and power efficiency, 4th Generation Tensor Cores: Up to 2X AI performance, 3rd Generation RT Cores: Up to 2X ray tracing performance, Axial-tech fans scaled up for 23% more airflow, and Dual Ball Fan Bearings last up to twice as long as conventional designs.",
      "Price": 1125.55,
      "MSRP": 1224.55,
      "QtyOnHand": 11,
      "QtyOnBackOrder": 6,
      "GraphicName": "ASUS TUF Gaming GeForce RTX 4080 OC.png",
      "Memory": "16GB GDDR6X",
      "Processor": "NVIDIA Ada Lovelace Streaming Multiprocessors",
      "Graphics": "NVIDIA® GeForce RTX™ 4080",
      "Storage": "OC mode: 2625 MHz"
    },
    {
      "Brand": "Alienware",
      "BrandName": "Alienware",
      "Category": "Laptop",
      "ProductName": "X16 R1 Gaming",
      "RAM": "32 GB",
      "Description": "Alienware X16 R1 Gaming Laptop - 16-inch QHD+ 240Hz Display, Core i9-13900HK, 32GB LPDDR5 RAM, 1TB SSD, NVIDIA GeForce RTX 4080 12GB GDDR6, Windows 11 Home, 1 Year Premium Support * Lunar Silver.",
      "Price": 3009.99,
      "MSRP": 3299.99,
      "QtyOnHand": 11,
      "QtyOnBackOrder": 6,
      "GraphicName": "Alienware Gaming Laptop.png",
      "Memory": "16 GB: LPDDR5, 6000 MT/s (onboard)",
      "Processor": "13th Gen Intel® Core™ i9-13900HK (24 MB cache, 14 cores, 20 threads, up to 5.40 GHz Turbo)",
      "Graphics": "NVIDIA® GeForce RTX™ 4080, 12 GB GDDR6",
      "Storage": "1 TB RAID 0 (2 x 512 GB), M.2, PCIe NVMe, SSD"
    },
    {
      "Brand": "ZOTAC",
      "BrandName": "ZOTAC",
      "Category": "Graphics Card",
      "ProductName": "GeForce RTX 4070 Ti",
      "RAM": "12 GB",
      "Description": "Powered by NVIDIA DLSS 3, ultra-efficient Ada Lovelace arch, and full ray tracing, Boost Clock 2625 MHz, 12GB GDDR6X, 192-bit, 21 Gbps, PCIE 4.0, IceStorm 2.0 Advanced Cooling, SPECTRA 2.0 ARGB Lighting, 3x 90mm fans, FREEZE Fan Stop, Active Fan Control, Metal Backplate, Bundled GPU Support Stand and 8K Ready, 4 Display Ready, HDCP 2.3, VR Ready. With 3 x DisplayPort 1.4a, 1 x HDMI 2.1a, DirectX 12 Ultimate, Vulkan RT API, Vulkan 1.3, OpenGL 4.6",
      "Price": 755.99,
      "MSRP": 819.99,
      "QtyOnHand": 5,
      "QtyOnBackOrder": 12,
      "GraphicName": "ZotacGeForceRTX4070Ti.png",
      "Memory": "12GB GDDR6X",
      "Processor": "NVIDIA Ada Lovelace architecture and DLSS 3",
      "Graphics": "IceStorm 2.0 Advanced Cooling",
      "Storage": "3 x DisplayPort 1.4a (up to 7680x4320@60Hz)"
    },
    {
      "Brand": "ASUS",
      "BrandName": "ASUS",
      "Category": "Laptop",
      "ProductName": "ROG Strix G16",
      "RAM": "16 GB",
      "Description": "13th Gen Intel Core i9-13980HX processor, and an NVIDIA GeForce RTX 4070 Laptop GPU at 140W Max TGP. BLAZING FAST MEMORY AND STORAGE * Multitask swiftly with 16GB of DDR5-4800MHz memory and speed up loading times with 1TB of PCIe 4x4. ROG INTELLIGENT COOLING * To put this amount of power in a gaming laptop, you need an even better cooling solution. The Strix features Thermal Grizzlys Conductonaut Extreme liquid metal on the CPU, and a third intake fan among other premium features. SWIFT VISUALS * The Strix G16 has a fast FHD 165Hz panel. Covers 100% of the sRGB color space and feature Dolby Vision, Adaptive-Sync support, and an 90% screen-to-body ratio for a stellar gaming and viewing experience.",
      "Price": 1599.99,
      "MSRP": 1999.99,
      "QtyOnHand": 5,
      "QtyOnBackOrder": 12,
      "GraphicName": "ASUS Laptop.png",
      "Memory": "Max Capacity: 32GB",
      "Processor": "13th Gen Intel® Core™ i9-13980HX Processor 2.2 GHz (36M Cache, up to 5.6 GHz, 24 cores: 8 P-cores and 16 E-cores)",
      "Graphics": "NVIDIA® GeForce RTX™ 4070 Laptop GPU",
      "Storage": "1TB PCIe® 4.0 NVMe™ M.2 SSD"
    },
    {
      "Brand": "MSI",
      "BrandName": "MSI",
      "Category": "Graphics Card",
      "ProductName": "MSI GeForce RTX 4070",
      "RAM": "12 GB",
      "Description": "Video Memory: 12GB GDDR6X, Memory Interface: 192-bit, Output: DisplayPort x 3 (v1.4a) / HDMI 2.1 x 1, Digital maximum resolution: 7680 x 4320.",
      "Price": 599.99,
      "MSRP": 699.99,
      "QtyOnHand": 22,
      "QtyOnBackOrder": 0,
      "GraphicName": "MsiGeForceRTX4070Ti.png",
      "Memory": "12GB GDDR6X DLSS 3",
      "Processor": "NVIDIA® GeForce RTX™ 4070",
      "Graphics": "PCI Express® Gen 4",
      "Storage": "Extreme Performance: 2625 MHz (MSI Center) Boost: 2610 MHz"
    },
    {
      "Brand": "CyberpowerPC",
      "BrandName": "CyberpowerPC",
      "Category": "Desktop",
      "ProductName": "CyberpowerPC Xtreme VR",
      "RAM": "16 GB",
      "Description": "System: Intel Core i9-13900KF 3.0GHz (8+16) Cores | Intel Z690 Chipset | 16GB DDR5 | 1TB PCIe NVMe SSD | Genuine Windows 11 Home 64-bit. Graphics: NVIDIA GeForce RTX 4070 Ti 12GB Video Card | 1x HDMI | 2x DisplayPorts. Connectivity: 6 x USB 3.1 | 2 x USB 2.0 | 1x RJ-45 Network Ethernet 10/100/1000 | 802.11AC Wi-Fi | Audio: 7.1 Channel | Keyboard and mouse. Special feature: Liquid cool CPU | 3-Piece Panoramic Tempered Glass Front/Side Case Panel | Custom RGB Case Lighting | USB Gaming Keyboard | 7 Colors RGB Gaming Mouse.",
      "Price": 2099.99,
      "MSRP": 2299.99,
      "QtyOnHand": 5,
      "QtyOnBackOrder": 12,
      "GraphicName": "CyberpowerPC.png",
      "Memory": "8GB DDR4 memory",
      "Processor": "Intel i5-6402P 2.80 GHz CPU.",
      "Graphics": "AMD Radeon RX 480 4GB GPU",
      "Storage": "1TB 7200 RPM hard drive"
    },
    {
      "Brand": "ZOTAC",
      "BrandName": "ZOTAC",
      "Category": "Graphics Card",
      "ProductName": "GeForce RTX 4060 Ti",
      "RAM": "8 GB",
      "Description": "Powered by NVIDIA DLSS 3, ultra-efficient Ada Lovelace arch, and full ray tracing, Boost Clock 2625 MHz, 12GB GDDR6X, 192-bit, 21 Gbps, PCIE 4.0, IceStorm 2.0 Advanced Cooling, SPECTRA RGB Lighting, 2x 90mm fans, FREEZE Fan Stop, Active Fan Control, Metal Backplate, Bundled GPU Support Stand and 8K Ready, 4 Display Ready, HDCP 2.3, VR Ready. With 3 x DisplayPort 1.4a, 1 x HDMI 2.1a, DirectX 12 Ultimate, Vulkan RT API, Vulkan 1.3, OpenGL 4.6",
      "Price": 275.99,
      "MSRP": 429.99,
      "QtyOnHand": 7,
      "QtyOnBackOrder": 25,
      "GraphicName": "ZotacGeForceRTX4060Ti.png",
      "Memory": "8GB GDDR6",
      "Processor": "GeForce RTX 4060 Ti",
      "Graphics": "4.0 x8",
      "Storage": "Boost: 2535MHz"
    },
    {
      "Brand": "Skytech Gaming",
      "BrandName": "Skytech",
      "Category": "Desktop",
      "ProductName": "Skytech Chronos Gaming PC",
      "RAM": "32GB DDR5 5200MHZ RGB",
      "Description": "AMD Ryzen 5 5600X 3.7GHz (4.6GHz Max Boost) CPU Processor | 1TB NVME SSD * Up to 30x Faster Than Traditional HDD. NVIDIA Geforce RTX 4070 Ti 12GB GDDR6X Graphics Card (Brand may vary) | 16GB DDR4 RAM 3200 Gaming Memory with Heat Spreader | Windows 11 Home 64-bit. 802.11 AC | No Bloatware | Graphic output options include 1 x HDMI, and 1 x Display Port Guaranteed, Additional Ports may vary | USB Ports Including 2.0, 3.0, and 3.2 Gen1 Ports | HD Audio and Mic | Free Gaming Keyboard and Mouse.",
      "Price": 1599.99,
      "MSRP": 1799.99,
      "QtyOnHand": 5,
      "QtyOnBackOrder": 12,
      "GraphicName": "Skytech Chronos Gaming PC.png",
      "Memory": "32GB DDR5 5200MHZ RGB",
      "Processor": "Intel i7 13700F",
      "Graphics": "Nvidia RTX 4060 Ti 8GB",
      "Storage": "1TB NVME"
    },
    {
      "Brand": "MSI",
      "BrandName": "MSI",
      "Category": "Graphics Card",
      "ProductName": "MSI GeForce RTX 4060 Ti",
      "RAM": "8 GB",
      "Description": "Video Memory: 8GB GDDR6, Memory Interface: 128-bit, Output: DisplayPort x 3 (v1.4a) / HDMI 2.1 x 1, Digital maximum resolution: 7680 x 4320.",
      "Price": 199.99,
      "MSRP": 399.99,
      "QtyOnHand": 1,
      "QtyOnBackOrder": 15,
      "GraphicName": "MsiGeForceRTX4060Ti.png",
      "Memory": "8GB GDDR6",
      "Processor": "PCI Express® Gen 4 x16 (uses x8)",
      "Graphics": "NVIDIA® GeForce RTX™ 4060 Ti",
      "Storage": "Extreme Performance: 2655 MHz (MSI Center) Boost: 2640 MHz"
    },
    {
      "Brand": "Gigabit",
      "BrandName": "Gigabit",
      "Category": "Graphics Card",
      "ProductName": "MSI GeForce RTX 3090",
      "RAM": "24 GB",
      "Description": "Triple Fan Thermal Design, Video Memory: 24GB GDDR6X, Memory Interface: 384-bit.Avoid using unofficial software, Output: DisplayPort x 3 (v1.4a) / HDMI 2.1 x 1.",
      "Price": 1000.95,
      "MSRP": 1224.31,
      "QtyOnHand": 7,
      "QtyOnBackOrder": 25,
      "GraphicName": "MSI Gaming GeForce RTX 3090.png",
      "Memory": "Integrated with 24GB GDDR6X 384-bit memory interface",
      "Processor": "NVIDIA Ampere Streaming Multiprocessors",
      "Graphics": "GeForce RTX™ 3090",
      "Storage": "Core Clock: 1755 MHz (Reference card: 1695 MHz)"
    },
    {
      "Brand": "HP",
      "BrandName": "HP",
      "Category": "Desktop",
      "ProductName": "OMEN 45L",
      "RAM": "16 GB",
      "Description": "Intel Core Processor advances real-world computing and delivers more ultra-efficient multi-tasking. Experience lifelike virtual worlds, ultra-high FPS gaming, revolutionary new ways to create and unprecedented workflow acceleration. DTS: X ULTRA TECHNOLOGY - By producing authentic, spatially accurate 3D sound through any headset, offers specially tuned audio modes for different game types to provide immersion for the best experience possible. KINGSTON FURY DDR5 MEMORY - With its high performance, everything from multi-tasking to playing games gets a boost. OMEN CRYO CHAMBER - Experience revolutionary cooling from the patented OMEN CRYO CHAMBER cooling system that enables the liquid cooler radiator to channel fresh, cold air from the surrounding environment to cool the CPU.",
      "Price": 1999.99,
      "MSRP": 2199.99,
      "QtyOnHand": 5,
      "QtyOnBackOrder": 12,
      "GraphicName": "OMEN Gaming PC.png",
      "Memory": "HyperX 64 GB DDR4-3467 MHz XMP RGB Heatsink RAM (4 x 16 GB)",
      "Processor": "Intel® Core™ i9-14900K (up to 6.0 GHz with Intel® Turbo Boost Technology, 36 MB L3 cache, 24 cores, 32 threads)",
      "Graphics": "NVIDIA® GeForce RTX™ 4090 (24 GB GDDR6X dedicated)",
      "Storage": "up to 2TB WD Black PCIe® Gen4 TLC M.2 SSD"
    },
    {
      "Brand": "ASUS",
      "BrandName": "ASUS",
      "Category": "Graphics Card",
      "ProductName": "TUF NVIDIA GeForce RTX 3090",
      "RAM": "24 GB",
      "Description": "NVIDIA Ampere Streaming Multiprocessors: The building blocks for the worlds fastest, most efficient GPU, the all-new Ampere SM brings 2X the FP32 throughput and improved power efficiency. 2nd Generation RT Cores: Experience 2X the throughput of 1st Gen RT Cores, plus concurrent RT and shading for a whole new level of ray tracing performance. 3rd Generation Tensor Cores: Get up to 2X the throughput with structural sparsity and advanced AI algorithms such as DLSS. Now with support for up to 8K resolution, these cores deliver a massive boost in game performance and all-new AI capabilities.",
      "Price": 1229.99,
      "MSRP": 1429.99,
      "QtyOnHand": 20,
      "QtyOnBackOrder": 0,
      "GraphicName": "AsusTuffNvidiaGeForce3090OC.png",
      "Memory": "24GB GDDR6X",
      "Processor": "NVIDIA® GeForce RTX™ 3090",
      "Graphics": "Digital Max Resolution 7680 x 4320",
      "Storage": "Gaming mode : 1740 MHz (Boost Clock"
    },
    {
      "Brand": "EVGA",
      "BrandName": "EVGA",
      "Category": "Graphics Card",
      "ProductName": "EVGA GeForce RTX 3090",
      "RAM": "24 GB",
      "Description": "Digital Max Resolution:7680 x 4320.590.4GT/s Texture Fill Rate, Real boost clock: 1800 MHz; Memory detail: 24576 MB GDDR6X, Real-time ray tracing in games for cutting-edge, hyper-realistic graphics, Triple HDB fans 9 iCX3 thermal sensors offer higher performance cooling and much quieter acoustic noiseAvoid using unofficial software, and All-metal backplate & adjustable ARGB.",
      "Price": 1159.95,
      "MSRP": 1459.95,
      "QtyOnHand": 7,
      "QtyOnBackOrder": 10,
      "GraphicName": "EVGA GeForce RTX 3080.png",
      "Memory": "24576 MB GDDR6X",
      "Processor": "NVIDIA GeForce RTX 3090",
      "Graphics": "7680 x 4320.590.4GT/s Texture Fill Rate",
      "Storage": "1800 MHz"
    },
    {
      "Brand": "EVGA",
      "BrandName": "EVGA",
      "Category": "Graphics Card",
      "ProductName": "GeForce RTX 3080 XC3",
      "RAM": "10 GB",
      "Description": "Real boost clock: 1710 MHz; Memory detail: 10240 MB GDDR6X, Real-time ray tracing in games for cutting-edge, hyper-realistic graphics, and Triple HDB fans offer higher performance cooling and much quieter acoustic noise.",
      "Price": 399.99,
      "MSRP": 599.99,
      "QtyOnHand": 2,
      "QtyOnBackOrder": 30,
      "GraphicName": "EvgaGeForceRTX3090CX3.png",
      "Memory": "10240MB GDDR6X",
      "Processor": "NVIDIA® GeForce RTX 3090 XC3",
      "Graphics": "4K 120Hz HDR, 8K 60Hz HDR",
      "Storage": "19000 MHz Effective"
    },
    {
      "Brand": "Acer",
      "BrandName": "Acer",
      "Category": "Desktop",
      "ProductName": "Acer Predator Helios 18",
      "RAM": "16 GB",
      "Description": "Drives: 1TB SSD\n Display: 8 GB NVIDIA GeForce RTX 4060 Graphics\n Communication: Wi-Fi 6E + Bluetooth 5.3",
      "Price": 1499.99,
      "MSRP": 1849.99,
      "QtyOnHand": 2,
      "QtyOnBackOrder": 0,
      "GraphicName": "AcerPredator.png",
      "Memory": "32 GB, DDR5 SDRAM",
      "Processor": "Intel® Core™ i9-13900HX processor Tetracosa-core (24 Core™) 2.20 GHz",
      "Graphics": "NVIDIA® GeForce RTX™ 4080 with 12 GB dedicated memory",
      "Storage": "1 TB"
  },
  {
      "Brand": "ASUS",
      "BrandName": "ASUS",
      "Category": "Laptop",
      "ProductName": "ASUS ROG Zephyrus G14",
      "RAM": "16 GB",
      "Description": "The ASUS ROG Zephyrus G14 14 Gaming Laptop is a powerful machine that can handle all your gaming needs. With an AMD Ryzen CPU, high-speed RAM and GeForce RTX 3050 graphics card, this laptop lets you play AAA games with ease. The WUXGA display with 144Hz refresh rate offers stunning visuals for an immersive experience.",
      "Price": 1545.55,
      "MSRP": 1699.99,
      "QtyOnHand": 3,
      "QtyOnBackOrder": 0,
      "GraphicName": "AsusZephyrus.png",
      "Memory": "8GB DDR4 on board\n 8GB DDR4-3200 SO-DIMM\n Max Capacity:24GB",
      "Processor": "AMD Ryzen™ 7 4800HS Mobile Processor (8-core/16-thread, 12MB Cache, 4.2 GHz max boost)",
      "Graphics": "NVIDIA® GeForce® GTX 1660Ti with Max-Q Design 6GB GDDR6",
      "Storage": "512GB PCIe® 3.0 NVMe™ M.2 SSD"
  },
  {
      "Brand": "Alienware",
      "BrandName": "Alienware",
      "Category": "Laptop",
      "ProductName": "Alienware M18 Gaming Laptop",
      "RAM": "16 GB",
      "Description": "Outplay your rivals and show them who's boss with an 18-inch gaming laptop featuring AMD Ryzen™ 7045 Series Processors for mobile and either AMD Radeon™ RX 7000M Series graphics or NVIDIA® GeForce RTX™ 40 Series graphics cards. Play your most demanding games with 250W Total Power Performance with more headroom to support overclocking without throttling",
      "Price": 3195.99,
      "MSRP": 3499.99,
      "QtyOnHand": 6,
      "QtyOnBackOrder": 0,
      "GraphicName": "AlienwareM18.png",
      "Memory": "32 GB: 2 x 16 GB, DDR5, 4800 MT/s",
      "Processor": "13th Gen Intel® Core™ i9-13900HX (36 MB cache, 24 cores, 32 threads, up to 5.40 GHz Turbo)",
      "Graphics": "NVIDIA® GeForce RTX™ 4080, 12 GB GDDR6",
      "Storage": "1 TB, M.2, PCIe NVMe, SSD"
  },
  {
      "Brand": "Razer",
      "BrandName": "Razer",
      "Category": "Desktop",
      "ProductName": "Maingear R1",
      "RAM": "16 GB DDR4",
      "Description": "Fully compatible with Razer Chroma, the R1 is the ultimate PC for the elite Razer fan. Customize your PC and RGB to your exact specification",
      "Price": 1549.99,
      "MSRP": 1849.99,
      "QtyOnHand": 8,
      "QtyOnBackOrder": 0,
      "GraphicName": "MaingearR1.png",
      "Memory": "16GB T-FORCE DELTA RGB DDR4",
      "Processor": "Intel® Core™ i5-14400f",
      "Graphics": "NVIDIA® GeForce RTX™ 4060",
      "Storage": "1TB T-FORCE A440 PRO"
  },
  {
      "Brand": "Maingear",
      "BrandName": "Maingear",
      "Category": "Desktop",
      "ProductName": "Maingear MG-1 Ruby",
      "RAM": "16 GB DDR5",
      "Description": "4070 Super | 7800X3D | 16GB DDR5 | 1TB SSD | 850W | Win 11 Home \nBring your games to the next level with the all-new MAINGEAR MG-1. Crafted for advanced performance, unlimited customization, and understated simplicity. Double your RAM, storage and upgrade to Windows 11 Pro with the Boost button for even more performance",
      "Price": 1549.99,
      "MSRP": 1999.99,
      "QtyOnHand": 4,
      "QtyOnBackOrder": 0,
      "GraphicName": "MaingearM1.png",
      "Memory": "16GB RGB DDR5 5200MT/s (2x8GB)",
      "Processor": "AMD Ryzen 7 7800X3D (8 Cores / 16 Threads)",
      "Graphics": "NVIDIA GeForce RTX 4070 Super (12GB GDDR6X)",
      "Storage": "1TB Gen4 M.2 NVMe SSD"
  }
  ]